{
  "topic": "線束設計",
  "sub_topic": "鐵殼連接器焊接規範",
  "content_type": "table",
  "keywords": [
    "裸線焊接",
    "連接器",
    "鐵殼",
    "20454系列",
    "焊點位置"
  ],
  "difficulty_level": "intermediate",
  "technical_symbols": [
    "mm",
    "MAX"
  ],
  "document_section": "第15章",
  "equipment_mentioned": [
    "HP機"
  ],
  "materials_mentioned": [
    "裸線",
    "鐵殼",
    "助焊劑",
    "焊錫"
  ],
  "processes_mentioned": [
    "焊接",
    "平行插入",
    "90度弯角出線",
    "沾助焊劑加錫"
  ],
  "standards_mentioned": [
    "高度1.55mmMAX",
    "高度2.7mmMAX"
  ],
  "measurements_units": [
    "mm"
  ],
  "safety_requirements": [
    "避免烫伤線材",
    "防止裸線焊錫過長刺破線材"
  ],
  "quality_criteria": [
    "鐵殼不超過紅色線標示處",
    "不可與邊緣線材重疊",
    "焊點不可超出與對插治具接觸區域",
    "不可採用往鐵殼上塗助焊劑後加錫"
  ],
  "application_area": "電子",
  "target_audience": "製造工程師、技術員",
  "action_items": [
    "裸線沾助焊劑後加錫",
    "避免鐵殼上殘留助焊劑"
  ],
  "related_documents": [
    "產品設計規範"
  ],
  "revision_info": "第29頁",
  "importance_level": "high"
}