{
  "topic": "線束設計",
  "sub_topic": "SATA連接線",
  "content_type": "product introduction",
  "keywords": [
    "SATA cable",
    "台式機",
    "連接線",
    "硬盤",
    "光驅"
  ],
  "difficulty_level": "basic",
  "technical_symbols": [
    "7P"
  ],
  "document_section": "產品介紹",
  "equipment_mentioned": [
    "台式機",
    "主板",
    "硬盤",
    "光驅"
  ],
  "materials_mentioned": [
    "SATA cable",
    "金屬卡扣"
  ],
  "processes_mentioned": [
    "連接主板和硬盤",
    "連接主板和光驅"
  ],
  "standards_mentioned": [],
  "measurements_units": [],
  "safety_requirements": [],
  "quality_criteria": [],
  "application_area": "電子",
  "target_audience": "技術員",
  "action_items": [],
  "related_documents": [],
  "revision_info": "",
  "importance_level": "medium"
}