{
  "topic": "品質檢驗流程",
  "sub_topic": "圖面公差檢驗規範",
  "content_type": "procedure",
  "keywords": [
    "公差",
    "檢驗",
    "簽章",
    "品管",
    "客戶料號"
  ],
  "difficulty_level": "intermediate",
  "technical_symbols": [
    "±",
    "#"
  ],
  "document_section": "品質檢驗章節",
  "equipment_mentioned": [],
  "materials_mentioned": [
    "零部件"
  ],
  "processes_mentioned": [
    "檢驗流程",
    "簽章確認"
  ],
  "standards_mentioned": [
    "公差範圍標準"
  ],
  "measurements_units": [],
  "safety_requirements": [],
  "quality_criteria": [
    "公差範圍檢驗",
    "194.3±2表示允收範圍為192.3-196.3"
  ],
  "application_area": "製造業",
  "target_audience": [
    "品管人員",
    "工程部門人員",
    "檢驗員"
  ],
  "action_items": [
    "工程部門主管簽章確認",
    "加盖工程部红色条行章",
    "注明客户料号",
    "檢查零部件規格是否符合圖面要求"
  ],
  "related_documents": [
    "圖面",
    "公差表"
  ],
  "revision_info": "",
  "importance_level": "high"
}